[
  {
    "user": {
      "type": "player",
      "name": "jcomcl",
      "uniqueId": "c392bc36-586f-433f-a6f5-204f35055380"
    },
    "time": 1729166182999,
    "type": "Profiler",
    "data": {
      "type": "url",
      "value": "https://spark.lucko.me/xbYwFQ4HZX"
    }
  },
  {
    "user": {
      "type": "player",
      "name": "jcomcl",
      "uniqueId": "c392bc36-586f-433f-a6f5-204f35055380"
    },
    "time": 1729166003292,
    "type": "Profiler",
    "data": {
      "type": "url",
      "value": "https://spark.lucko.me/YVoMUmy4dU"
    }
  }
]